{
  "contacts" : [
  {
    "contactId": 3,
    "agencyId": 1,
    "firstName": "Test",
    "lastName": "TestLast3",
    "businessUnit": "test 2 business unit",
    "title": "test title 3",
    "homePhone": "5188675309",
    "cellPhone": "5188675309",
    "workPhone": "5188675309",
    "extension": null,
    "workCellPhone": "5188675309",
    "email": "test.testLast3@test.com",
    "createdTime": "2019-07-17T10:25:34.5588012",
    "modifiedTime": "0001-01-01T00:00:00",
    "logicalDeleteDate": "0001-01-01T00:00:00",
    "uuid": "2190495e-70e0-4a7c-ae77-c41c93cd8e3a",
    "agency": {
      "agencyId": 1,
      "authenticationTypeId": 1,
      "agencyName": "Test Agency 1",
      "createdTime": "2019-07-17T10:25:34.5575473",
      "modifiedTime": "0001-01-01T00:00:00",
      "logicalDeleteDate": "0001-01-01T00:00:00",
      "uuid": "00a4f5c2-cb6f-4718-8dab-60e1de993776",
      "authenticationTypes": null,
      "agencyCustomField": null,
      "contact": null,
      "user": null,
      "securityLevel": null
    },
    "customValue": []
  },
  {
    "contactId": 4,
    "agencyId": 1,
    "firstName": "Test",
    "lastName": "TestLast4",
    "businessUnit": "test 1 business unit",
    "title": "test title 4",
    "homePhone": "5188675309",
    "cellPhone": "5188675309",
    "workPhone": "5188675309",
    "extension": null,
    "workCellPhone": "5188675309",
    "email": "test.testLast4@test.com",
    "createdTime": "2019-07-17T10:25:34.5588018",
    "modifiedTime": "0001-01-01T00:00:00",
    "logicalDeleteDate": "0001-01-01T00:00:00",
    "uuid": "ef1d56ac-2c38-4b55-97dc-bc5e12842769",
    "agency": {
      "agencyId": 1,
      "authenticationTypeId": 1,
      "agencyName": "Test Agency 1",
      "createdTime": "2019-07-17T10:25:34.5575473",
      "modifiedTime": "0001-01-01T00:00:00",
      "logicalDeleteDate": "0001-01-01T00:00:00",
      "uuid": "00a4f5c2-cb6f-4718-8dab-60e1de993776",
      "authenticationTypes": null,
      "agencyCustomField": null,
      "contact": null,
      "user": null,
      "securityLevel": null
    },
    "customValue": []
  },
  {
    "contactId": 5,
    "agencyId": 2,
    "firstName": "Test",
    "lastName": "TestLast5",
    "businessUnit": "test 1 business unit",
    "title": "test title 5",
    "homePhone": "5188675309",
    "cellPhone": "5188675309",
    "workPhone": "5188675309",
    "extension": null,
    "workCellPhone": "5188675309",
    "email": "test.testLast5@test.com",
    "createdTime": "2019-07-17T10:25:34.5588021",
    "modifiedTime": "0001-01-01T00:00:00",
    "logicalDeleteDate": "0001-01-01T00:00:00",
    "uuid": "3a2433ac-b275-4e41-b46a-05dc0a0ef181",
    "agency": {
      "agencyId": 2,
      "authenticationTypeId": 1,
      "agencyName": "Test Agency 2",
      "createdTime": "2019-07-17T10:25:34.5575953",
      "modifiedTime": "0001-01-01T00:00:00",
      "logicalDeleteDate": "0001-01-01T00:00:00",
      "uuid": "b60e548e-e710-40d5-bf76-ba46a91bd5d2",
      "authenticationTypes": null,
      "agencyCustomField": null,
      "contact": null,
      "user": null,
      "securityLevel": null
    },
    "customValue": [
      {
        "customValueId": 1,
        "contactId": 5,
        "customFieldId": 1,
        "answerText": "text answer",
        "createdTime": "2019-07-17T10:25:34.5589274",
        "modifiedTime": "0001-01-01T00:00:00",
        "logicalDeleteDate": "0001-01-01T00:00:00",
        "uuid": "ad3270d4-ab56-49a9-b3ec-bf2838d7911e",
        "customField": {
          "customFieldId": 1,
          "securityLevelId": 1,
          "fieldType": "text",
          "fieldText": "Text Field",
          "choiceOptions": null,
          "isRequired": "n",
          "createdTime": "2019-07-17T10:25:34.5583192",
          "modifiedTime": "0001-01-01T00:00:00",
          "logicalDeleteDate": "0001-01-01T00:00:00",
          "uuid": "1e8538dc-074f-4786-a52b-0d1263f4d06c",
          "customValue": null,
          "agencyCustomField": null
        }
      },
      {
        "customValueId": 2,
        "contactId": 5,
        "customFieldId": 2,
        "answerText": "test 2",
        "createdTime": "2019-07-17T10:25:34.5589746",
        "modifiedTime": "0001-01-01T00:00:00",
        "logicalDeleteDate": "0001-01-01T00:00:00",
        "uuid": "47110f87-635d-42a1-8a60-293414b57596",
        "customField": {
          "customFieldId": 2,
          "securityLevelId": 2,
          "fieldType": "choice",
          "fieldText": "Choice Field",
          "choiceOptions": "test 1, test 2, test 3",
          "isRequired": "n",
          "createdTime": "2019-07-17T10:25:34.5583796",
          "modifiedTime": "0001-01-01T00:00:00",
          "logicalDeleteDate": "0001-01-01T00:00:00",
          "uuid": "719929ad-4c57-4c20-8057-828c891a7d22",
          "customValue": null,
          "agencyCustomField": null
        }
      },
      {
        "customValueId": 3,
        "contactId": 5,
        "customFieldId": 3,
        "answerText": "this is a test text box answer.  it should be long",
        "createdTime": "2019-07-17T10:25:34.5589767",
        "modifiedTime": "0001-01-01T00:00:00",
        "logicalDeleteDate": "0001-01-01T00:00:00",
        "uuid": "ae15e1ba-dae6-4253-b23a-83b42e75579e",
        "customField": {
          "customFieldId": 3,
          "securityLevelId": 3,
          "fieldType": "textbox",
          "fieldText": "Text Box",
          "choiceOptions": null,
          "isRequired": "n",
          "createdTime": "2019-07-17T10:25:34.5583814",
          "modifiedTime": "0001-01-01T00:00:00",
          "logicalDeleteDate": "0001-01-01T00:00:00",
          "uuid": "8486d48f-3630-4a2f-800f-2be9a646b654",
          "customValue": null,
          "agencyCustomField": null
        }
      }
    ]
  },
  {
    "contactId": 6,
    "agencyId": 2,
    "firstName": "Test",
    "lastName": "TestLast6",
    "businessUnit": "test 2 business unit",
    "title": "test title 6",
    "homePhone": "5188675309",
    "cellPhone": "5188675309",
    "workPhone": "5188675309",
    "extension": null,
    "workCellPhone": "5188675309",
    "email": "test.testLast6@test.com",
    "createdTime": "2019-07-17T10:25:34.558803",
    "modifiedTime": "0001-01-01T00:00:00",
    "logicalDeleteDate": "0001-01-01T00:00:00",
    "uuid": "1c3433ef-8fe9-4aec-88fa-dff2efc690cf",
    "agency": {
      "agencyId": 2,
      "authenticationTypeId": 1,
      "agencyName": "Test Agency 2",
      "createdTime": "2019-07-17T10:25:34.5575953",
      "modifiedTime": "0001-01-01T00:00:00",
      "logicalDeleteDate": "0001-01-01T00:00:00",
      "uuid": "b60e548e-e710-40d5-bf76-ba46a91bd5d2",
      "authenticationTypes": null,
      "agencyCustomField": null,
      "contact": null,
      "user": null,
      "securityLevel": null
    },
    "customValue": [
      {
        "customValueId": 4,
        "contactId": 6,
        "customFieldId": 1,
        "answerText": "text answer 2",
        "createdTime": "2019-07-17T10:25:34.558977",
        "modifiedTime": "0001-01-01T00:00:00",
        "logicalDeleteDate": "0001-01-01T00:00:00",
        "uuid": "f2635c64-98ff-43c9-be58-a69c912b66d2",
        "customField": {
          "customFieldId": 1,
          "securityLevelId": 1,
          "fieldType": "text",
          "fieldText": "Text Field",
          "choiceOptions": null,
          "isRequired": "n",
          "createdTime": "2019-07-17T10:25:34.5583192",
          "modifiedTime": "0001-01-01T00:00:00",
          "logicalDeleteDate": "0001-01-01T00:00:00",
          "uuid": "1e8538dc-074f-4786-a52b-0d1263f4d06c",
          "customValue": null,
          "agencyCustomField": null
        }
      },
      {
        "customValueId": 5,
        "contactId": 6,
        "customFieldId": 2,
        "answerText": "test 1",
        "createdTime": "2019-07-17T10:25:34.5589776",
        "modifiedTime": "0001-01-01T00:00:00",
        "logicalDeleteDate": "0001-01-01T00:00:00",
        "uuid": "8d9382b6-b46d-4694-90f0-a105469e1e55",
        "customField": {
          "customFieldId": 2,
          "securityLevelId": 2,
          "fieldType": "choice",
          "fieldText": "Choice Field",
          "choiceOptions": "test 1, test 2, test 3",
          "isRequired": "n",
          "createdTime": "2019-07-17T10:25:34.5583796",
          "modifiedTime": "0001-01-01T00:00:00",
          "logicalDeleteDate": "0001-01-01T00:00:00",
          "uuid": "719929ad-4c57-4c20-8057-828c891a7d22",
          "customValue": null,
          "agencyCustomField": null
        }
      },
      {
        "customValueId": 6,
        "contactId": 6,
        "customFieldId": 3,
        "answerText": "this is a test text box answer.  it should be long 2",
        "createdTime": "2019-07-17T10:25:34.5589779",
        "modifiedTime": "0001-01-01T00:00:00",
        "logicalDeleteDate": "0001-01-01T00:00:00",
        "uuid": "2c3eb21f-67b7-4e6f-9365-20a96a8244d2",
        "customField": {
          "customFieldId": 3,
          "securityLevelId": 3,
          "fieldType": "textbox",
          "fieldText": "Text Box",
          "choiceOptions": null,
          "isRequired": "n",
          "createdTime": "2019-07-17T10:25:34.5583814",
          "modifiedTime": "0001-01-01T00:00:00",
          "logicalDeleteDate": "0001-01-01T00:00:00",
          "uuid": "8486d48f-3630-4a2f-800f-2be9a646b654",
          "customValue": null,
          "agencyCustomField": null
        }
      },
      {
        "customValueId": 8,
        "contactId": 6,
        "customFieldId": 3,
        "answerText": "resr",
        "createdTime": "2019-07-17T10:25:34.5589746",
        "modifiedTime": "2019-07-17T10:25:34.5589746",
        "logicalDeleteDate": "2019-07-17T10:25:34.5589746",
        "uuid": "47110f87-635d-42a1-8a60-293414b57596",
        "customField": {
          "customFieldId": 3,
          "securityLevelId": 3,
          "fieldType": "textbox",
          "fieldText": "Text Box",
          "choiceOptions": null,
          "isRequired": "n",
          "createdTime": "2019-07-17T10:25:34.5583814",
          "modifiedTime": "0001-01-01T00:00:00",
          "logicalDeleteDate": "0001-01-01T00:00:00",
          "uuid": "8486d48f-3630-4a2f-800f-2be9a646b654",
          "customValue": null,
          "agencyCustomField": null
        }
      }
    ]
  }
]
}
